nlu/__init__.py
nlu/data.py
nlu/error.py
nlu/error_analysis.py
nlu/error_structure.py
nlu/parser.py
nlu/parser_utils.py
nlu/utils.py
nlu/ext_utils/__init__.py
nlu/ext_utils/confusion_matrix_pretty_print.py
ner_error_analysis-0.2.dist-info/METADATA
ner_error_analysis-0.2.dist-info/WHEEL
ner_error_analysis-0.2.dist-info/top_level.txt
ner_error_analysis-0.2.dist-info/RECORD
