Metadata-Version: 2.1
Name: ner-error-analysis
Version: 0.2
Summary: NER Error Analysis for column (conll format) dataset including CoNLL-2003, WNUT-2017, ...
Home-page: https://github.com/ciaochiaociao/ner_error_analysis
Author: Chiao-Wei Hsu
Author-email: tony790927@gmail.com
License: UNKNOWN
Platform: UNKNOWN
Classifier: Programming Language :: Python :: 3
Classifier: License :: OSI Approved :: MIT License
Classifier: Operating System :: OS Independent
Requires-Python: >=3.6
